banana_cli/__init__.py
banana_cli/api.py
banana_cli/cli.py
banana_cli/cmd_dev.py
banana_cli/rick.py
banana_cli/server.py
banana_cli/utils.py
banana_cli/process/__init__.py
banana_cli/process/cells.py
banana_cli/process/run.py
banana_cli-0.1.2.dist-info/LICENSE
banana_cli-0.1.2.dist-info/METADATA
banana_cli-0.1.2.dist-info/WHEEL
banana_cli-0.1.2.dist-info/entry_points.txt
banana_cli-0.1.2.dist-info/top_level.txt
banana_cli-0.1.2.dist-info/RECORD
