Metadata-Version: 2.1
Name: banana-cli
Version: 0.1.2
Summary: The Banana CLI helps you build Potassium apps
Home-page: https://www.banana.dev
Author: Erik Dunteman
Author-email: erik@banana.dev
License: Apache License 2.0
Keywords: Banana server,HTTP server,Banana,Framework
Classifier: Development Status :: 3 - Alpha
Classifier: Intended Audience :: Developers
Classifier: Topic :: Software Development :: Build Tools
Classifier: License :: OSI Approved :: MIT License
Classifier: Programming Language :: Python :: 3.7
Classifier: Programming Language :: Python :: 3.8
Classifier: Programming Language :: Python :: 3.9
Requires-Python: >=3.7
License-File: LICENSE
Requires-Dist: Click
Requires-Dist: gitpython
Requires-Dist: termcolor
Requires-Dist: requests
Requires-Dist: yaspin
Requires-Dist: prompt-toolkit
Requires-Dist: opencv-python
Requires-Dist: gitignore-parser
Requires-Dist: fastapi
Requires-Dist: uvicorn[standard]
Requires-Dist: websocket-client
Requires-Dist: wsaccel
Requires-Dist: rel
